{
  "type": "minecraft:generic",
  "pools": [
    {
      "rolls": 1,
      "entries": [
        {
          "type": "minecraft:item",
          "name": "minecraft:jigsaw",
          "functions": [
            {
              "function": "minecraft:set_lore",
              "lore": [
                {
                  "text": "Creepers suddenly feel like celebrating!"
                }
              ]
            },
            {
              "function": "minecraft:set_name",
              "name": {
                "text": "Creeper Defuser",
                "color": "blue",
                "italic": false
              }
            },
            {
              "function": "minecraft:set_nbt",
              "tag": "{paveral.anti_creeper_grief:1b,CustomModelData:1}"
            }
          ]
        }
      ]
    }
  ]
}
